r3l3453/__init__.py
r3l3453/__main__.py
r3l3453/cookiecutter/cookiecutter.json
r3l3453/cookiecutter/hooks/post_gen_project.py
r3l3453/cookiecutter/{{cookiecutter.project_name}}/LICENCE.txt
r3l3453/cookiecutter/{{cookiecutter.project_name}}/README.rst
r3l3453/cookiecutter/{{cookiecutter.project_name}}/pyproject_template.toml
r3l3453/cookiecutter/{{cookiecutter.project_name}}/{{cookiecutter.project_name}}/__init__.py
r3l3453-0.54.2.dist-info/WHEEL
r3l3453-0.54.2.dist-info/entry_points.txt
r3l3453-0.54.2.dist-info/METADATA
r3l3453-0.54.2.dist-info/RECORD
