Metadata-Version: 2.3
Name: r3l3453
Version: 0.54.2
Summary: Bump version, tag, commit, release to pypi, bump again, and push.
Author: 5j9
Author-email: 5j9 <5j9@users.noreply.github.com>
License: GNU General Public License v3 (GPLv3)
Classifier: Intended Audience :: Developers
Classifier: License :: OSI Approved :: GNU General Public License v3 (GPLv3)
Classifier: Natural Language :: English
Classifier: Topic :: Software Development
Requires-Dist: cyclopts
Requires-Dist: ruff
Requires-Dist: cookiecutter
Requires-Dist: tomlkit
Requires-Dist: uv
Requires-Dist: loguru>=0.7.3
Requires-Python: >=3.12
Project-URL: GitHub, https://github.com/5j9/r3l3453
